binance_candle/__init__.py
binance_candle/utils.py
binance_candle/cmd/__init__.py
binance_candle/code/__init__.py
binance_candle/exception/__init__.py
binance_candle/exception/_base.py
binance_candle/exception/param.py
binance_candle/exception/req.py
binance_candle/exception/rule.py
binance_candle/market/__init__.py
binance_candle/market/_base.py
binance_candle/market/exchange_info.py
binance_candle/market/history_candle.py
binance_candle/market/ticker.py
binance_candle/server/__init__.py
binance_candle/server/rule.py
binance_candle/server/server.py
binance_candle-1.0.10.dist-info/METADATA
binance_candle-1.0.10.dist-info/WHEEL
binance_candle-1.0.10.dist-info/top_level.txt
binance_candle-1.0.10.dist-info/RECORD
